{
  "id": "core-concepts",
  "title": "Core concepts",
  "description": "This guide explains the core concepts and components that make up Tyler's architecture.",
  "source": "@site/docs/core-concepts.md",
  "sourceDirName": ".",
  "slug": "/core-concepts",
  "permalink": "/tyler/core-concepts",
  "draft": false,
  "unlisted": false,
  "editUrl": "https://github.com/adamwdraper/tyler/tree/main/docs/docs/core-concepts.md",
  "tags": [],
  "version": "current",
  "sidebarPosition": 4,
  "frontMatter": {
    "sidebar_position": 4
  },
  "sidebar": "documentationSidebar",
  "previous": {
    "title": "Chat with Tyler",
    "permalink": "/tyler/chat-with-tyler"
  },
  "next": {
    "title": "Overview",
    "permalink": "/tyler/tools/overview"
  }
}